st_on_hover_tabs_venrup/__init__.py
hoverTabs-1.0.0.dist-info/LICENSE
hoverTabs-1.0.0.dist-info/METADATA
hoverTabs-1.0.0.dist-info/WHEEL
hoverTabs-1.0.0.dist-info/top_level.txt
hoverTabs-1.0.0.dist-info/RECORD
