Metadata-Version: 2.1
Name: hoverTabs
Version: 1.0.0
Home-page: 
Author: Waqar Ahmad
Author-email: 
Requires-Python: >=3.6
License-File: LICENSE
Requires-Dist: streamlit (>=0.63)
